modalg/__init__.py
modalg/abelianGroup.py
modalg/comm_ring.py
modalg/field.py
modalg/group.py
modalg/myfunctions.py
modalg/ring.py
modalg-0.1.1.dist-info/METADATA
modalg-0.1.1.dist-info/WHEEL
modalg-0.1.1.dist-info/licenses/LICENSE.md
modalg-0.1.1.dist-info/RECORD
