Metadata-Version: 2.4
Name: modalg
Version: 0.1.1
Summary: Implements algebraic structures from abstract algebra
Project-URL: Homepage, https://github.com/SammySuliman/ModAlg
Project-URL: Issues, https://github.com/SammySuliman/ModAlg/issues
Author: Sammy Suliman
License: MIT License
License-File: LICENSE.md
Requires-Python: >=3.9
Requires-Dist: lark>=1.1.0
Requires-Dist: pyyaml>=6.0
